{
    "phrase_to_symbol": {
        "temperature": "T",
        "temp": "T",
        "pressure": "P",
        "humidity": "H",
        "voltage": "V",
        "current": "I",
        "power": "PWR",
        "speed": "SPD",
        "frequency": "FREQ",
        "resistance": "R",
        "capacity": "CAP",
        "degrees celsius": "C",
        "degrees fahrenheit": "F",
        "fan active": "FAN_ON",
        "fan inactive": "FAN_OFF",
        "fan on": "FAN_ON",
        "fan off": "FAN_OFF",
        "backup fan": "BKUP_FAN",
        "motor active": "MOT_ON",
        "motor inactive": "MOT_OFF",
        "system active": "SYS_ON",
        "system inactive": "SYS_OFF",
        "system online": "SYS_ON",
        "system offline": "SYS_OFF",
        "pump active": "PUMP_ON",
        "pump inactive": "PUMP_OFF",
        "sensor active": "SENS_ON",
        "sensor inactive": "SENS_OFF",
        "alarm triggered": "ALM_ON",
        "alarm active": "ALM_ON",
        "alarm off": "ALM_OFF",
        "warning level": "WARN_LVL",
        "critical level": "CRIT_LVL",
        "normal range": "NORM",
        "out of range": "OOR",
        "within range": "IN_RANGE",
        "maximum": "MAX",
        "minimum": "MIN",
        "threshold": "THR",
        "greater than": ">",
        "less than": "<",
        "equal to": "==",
        "not equal to": "!=",
        "greater than or equal to": ">=",
        "less than or equal to": "<="
    },
    "unit_symbols": {
        "°C": "C",
        "°F": "F",
        "degrees celsius": "C",
        "degrees fahrenheit": "F",
        "kilometers per hour": "KPH",
        "miles per hour": "MPH",
        "kilopascal": "kPa",
        "megapascal": "MPa",
        "kilowatt": "kW",
        "megawatt": "MW",
        "ampere": "A",
        "milliampere": "mA",
        "hertz": "Hz",
        "kilohertz": "kHz",
        "megahertz": "MHz"
    }
}